torchtools/__init__.py
torchtools/batch.py
torchtools/ddp.py
torchtools/deterministic.py
torchtools/graph.py
torchtools/images.py
torchtools/logging.py
torchtools/optimization.py
torchtools/typing.py
torchtools/videos.py
torchtools/modules/__init__.py
torchtools/modules/attention.py
torchtools/modules/feature_extractor.py
torchtools/modules/fully_connected.py
torchtools/modules/nce.py
torchtools/modules/pairwise_acc.py
torchtools/modules/placeholder.py
torchtools/modules/positional_embedding.py
torchtools/modules/utils.py
torchtools/tensors/__init__.py
torchtools/tensors/function.py
torchtools/tensors/tensor_group.py
torchtools/tensors/tensor_index.py
torchtools_cjwcommuny-0.0.10.dist-info/LICENSE
torchtools_cjwcommuny-0.0.10.dist-info/METADATA
torchtools_cjwcommuny-0.0.10.dist-info/WHEEL
torchtools_cjwcommuny-0.0.10.dist-info/top_level.txt
torchtools_cjwcommuny-0.0.10.dist-info/RECORD
