Metadata-Version: 2.1
Name: torchtools-cjwcommuny
Version: 0.0.10
Summary: Toolkit for Pytorch
Home-page: https://github.com/cjwcommuny/torch-tools
Author: cjwcommuny
Author-email: cjwcommuny@outlook.com
License: UNKNOWN
Platform: UNKNOWN
Classifier: Programming Language :: Python :: 3
Classifier: License :: OSI Approved :: MIT License
Classifier: Operating System :: OS Independent
Requires-Python: >=3.6
